binder/__init__.py
binder/exceptions.py
binder/history.py
binder/json.py
binder/middleware.py
binder/models.py
binder/orderable_agg.py
binder/router.py
binder/tests_discoverer.py
binder/utils.py
binder/view_logger.py
binder/views.py
binder/websocket.py
binder/management/__init__.py
binder/management/commands/__init__.py
binder/management/commands/binder_history_remove_reverse_spam.py
binder/migrations/0001_initial.py
binder/migrations/0002_change_diff.py
binder/migrations/0003_history_remove_reverse_spam.py
binder/migrations/0004_history_changeset_change_date.py
binder/migrations/__init__.py
binder/permissions/__init__.py
binder/permissions/views.py
binder/plugins/__init__.py
binder/plugins/my_filters/__init__.py
binder/plugins/my_filters/models.py
binder/plugins/my_filters/views.py
binder/plugins/my_filters/migrations/0001_initial.py
binder/plugins/my_filters/migrations/__init__.py
binder/plugins/token_auth/__init__.py
binder/plugins/token_auth/middleware.py
binder/plugins/token_auth/models.py
binder/plugins/token_auth/views.py
binder/plugins/token_auth/management/__init__.py
binder/plugins/token_auth/management/commands/__init__.py
binder/plugins/token_auth/management/commands/create_user_token.py
binder/plugins/token_auth/management/commands/delete_user_token.py
binder/plugins/token_auth/migrations/0001_initial.py
binder/plugins/token_auth/migrations/0002_add_related_name.py
binder/plugins/token_auth/migrations/0003_change_token_to_varchar_for_mysql_compat.py
binder/plugins/token_auth/migrations/__init__.py
binder/plugins/views/__init__.py
binder/plugins/views/csvexport.py
binder/plugins/views/file_hash_view.py
binder/plugins/views/image.py
binder/plugins/views/multi_request.py
binder/plugins/views/userview.py
tests/__init__.py
tests/compare.py
tests/test_annotations.py
tests/test_api_catchall.py
tests/test_file_uploads.py
tests/test_filter_manyrels.py
tests/test_filterable_relations.py
tests/test_hidden_fields.py
tests/test_history.py
tests/test_inheritance.py
django_binder-1.5.0.dist-info/LICENSE
django_binder-1.5.0.dist-info/METADATA
django_binder-1.5.0.dist-info/WHEEL
django_binder-1.5.0.dist-info/top_level.txt
django_binder-1.5.0.dist-info/RECORD
