Metadata-Version: 2.1
Name: django-binder
Version: 1.5.0
Summary: Code Yellow backend framework for SPA webapps with REST-like API.
Home-page: https://github.com/CodeYellowBV/django-binder
Author: Marcel Moreaux
Author-email: marcel@codeyellow.nl
License: MIT License
Platform: UNKNOWN
Classifier: Environment :: Web Environment
Classifier: Framework :: Django
Classifier: Framework :: Django :: 2.0
Classifier: Intended Audience :: Developers
Classifier: License :: OSI Approved :: MIT License
Classifier: Operating System :: OS Independent
Classifier: Programming Language :: Python
Classifier: Programming Language :: Python :: 3
Classifier: Programming Language :: Python :: 3.4
Classifier: Programming Language :: Python :: 3.5
Classifier: Topic :: Internet :: WWW/HTTP
Classifier: Topic :: Internet :: WWW/HTTP :: Dynamic Content
Requires-Dist: Django (>=2.0)
Requires-Dist: Pillow (>=3.2.0)
Requires-Dist: django-request-id (>=1.0.0)
Requires-Dist: requests (>=2.13.0)
